dvuploader/__init__.py
dvuploader/checksum.py
dvuploader/cli.py
dvuploader/config.py
dvuploader/directupload.py
dvuploader/dvuploader.py
dvuploader/file.py
dvuploader/nativeupload.py
dvuploader/packaging.py
dvuploader/utils.py
dvuploader-0.3.0.dist-info/LICENSE
dvuploader-0.3.0.dist-info/METADATA
dvuploader-0.3.0.dist-info/WHEEL
dvuploader-0.3.0.dist-info/entry_points.txt
dvuploader-0.3.0.dist-info/RECORD
