Metadata-Version: 2.3
Name: dvuploader
Version: 0.3.0
Summary: Python library for uploading (bulk) data to Dataverse
Author: Jan Range
Requires-Python: >=3.9,<4.0
Classifier: Programming Language :: Python :: 3
Classifier: Programming Language :: Python :: 3.9
Classifier: Programming Language :: Python :: 3.10
Classifier: Programming Language :: Python :: 3.11
Classifier: Programming Language :: Python :: 3.12
Classifier: Programming Language :: Python :: 3.13
Requires-Dist: aiofiles (>=24.1.0,<25.0.0)
Requires-Dist: httpx (>=0.28,<0.29)
Requires-Dist: nest-asyncio (>=1.5.8,<2.0.0)
Requires-Dist: pydantic (>=2.5.3,<3.0.0)
Requires-Dist: pyyaml (>=6.0.1,<7.0.0)
Requires-Dist: rich (>=13.7.0,<14.0.0)
Requires-Dist: tenacity (>=8.3.0,<9.0.0)
Requires-Dist: typer (>=0.9,<0.16)
